LICENSE.md
MANIFEST.in
README.md
README.rst
setup.py
papertrade/__init__.py
papertrade/calculations.py
papertrade/commands.py
papertrade/database.py
papertrade/main.py
papertrade/ui.py
papertrade.egg-info/PKG-INFO
papertrade.egg-info/SOURCES.txt
papertrade.egg-info/dependency_links.txt
papertrade.egg-info/entry_points.txt
papertrade.egg-info/not-zip-safe
papertrade.egg-info/requires.txt
papertrade.egg-info/top_level.txt