Metadata-Version: 1.1
Name: papertrade
Version: 0.1.0
Summary: Simple paper trading application for the terminal.
Home-page: https://github.com/morngrar/papertrade
Author: Svein-Kåre Bjørnsen
Author-email: sveinkare@gmail.com
License: GPL
Platform: UNKNOWN
Classifier: Development Status :: 3 - Alpha
Classifier: Intended Audience :: End Users/Desktop
Classifier: License :: OSI Approved :: GNU General Public License v3 (GPLv3)
Classifier: Programming Language :: Python :: 3 :: Only
Classifier: Topic :: Utilities
